Metadata-Version: 1.0
Name: nbpyhelp
Version: 0.1
Summary: A collection of helper functions for python
Home-page: http://github.com/nbhelpers/nbpyhelp
Author: Nick Barkas
Author-email: me@nikolasbarkas.com
License: MIT
Platform: UNKNOWN
